flask_auth/__init__.py
flask_auth/forms.py
flask_auth/routes.py
flask_auth/user_util.py
flask_auth/static/.DS_Store
flask_auth/static/css/style.css
flask_auth/static/js/particles.js
flask_auth/templates/display_qr.html
flask_auth/templates/login.html
flask_auth/templates/signup.html
flask_auth/templates/verify_otp.html
FlaskAuth2FA-1.7.5.dist-info/LICENSE
FlaskAuth2FA-1.7.5.dist-info/METADATA
FlaskAuth2FA-1.7.5.dist-info/WHEEL
FlaskAuth2FA-1.7.5.dist-info/top_level.txt
FlaskAuth2FA-1.7.5.dist-info/RECORD
