Metadata-Version: 2.1
Name: FlaskAuth2FA
Version: 1.7.5
Summary: A Flask extension for handling user authentication.
Author-email: Tim Kerr <timkerr222@gmail.com>
License: MIT
Project-URL: homepage, https://github.com/timkerr222/flask-auth-2fa
Classifier: Framework :: Flask
Classifier: License :: OSI Approved :: MIT License
Classifier: Programming Language :: Python :: 3
Classifier: Programming Language :: Python :: 3.7
Classifier: Programming Language :: Python :: 3.8
Classifier: Programming Language :: Python :: 3.9
Requires-Python: >=3.6
License-File: LICENSE
Requires-Dist: Flask
Requires-Dist: bcrypt
Requires-Dist: pyotp
Requires-Dist: Flask-WTF
Requires-Dist: email-validator
Requires-Dist: qrcode
Requires-Dist: wtforms
Requires-Dist: passlib
Requires-Dist: pillow
Requires-Dist: python-dotenv
